pdf417decoder/BarcodeArea.py
pdf417decoder/BarcodeInfo.py
pdf417decoder/BorderPattern.py
pdf417decoder/BorderSymbol.py
pdf417decoder/Decoder.py
pdf417decoder/ErrorCorrection.py
pdf417decoder/Modulus.py
pdf417decoder/Polynomial.py
pdf417decoder/StaticTables.py
pdf417decoder/__init__.py
pdf417decoder_with_opencv_python_headless-1.0.9.dist-info/LICENSE
pdf417decoder_with_opencv_python_headless-1.0.9.dist-info/METADATA
pdf417decoder_with_opencv_python_headless-1.0.9.dist-info/WHEEL
pdf417decoder_with_opencv_python_headless-1.0.9.dist-info/top_level.txt
pdf417decoder_with_opencv_python_headless-1.0.9.dist-info/RECORD
