Metadata-Version: 2.1
Name: pdf417decoder-with-opencv-python-headless
Version: 1.0.9
Summary: A PDF417 barcode decoder
Home-page: https://github.com/gabrielvannier/pdf417decoder-with-opencv-python-headless
Author: Sparkfish LLC
Author-email: packages@sparkfish.com
Project-URL: Bug Tracker, https://github.com/gabrielvannier/pdf417decoder-with-opencv-python-headless
Classifier: Programming Language :: Python :: 3
Classifier: License :: Other/Proprietary License
Classifier: Operating System :: OS Independent
Requires-Python: >=3.7
License-File: LICENSE
Requires-Dist: numpy >=1.20.1
Requires-Dist: opencv-python-headless >=4.6
Requires-Dist: pillow >=9.5.0
